README.rst
bootstrap.py
buildout.cfg
setup.py
collective/__init__.py
collective.js.formvalidation.egg-info/PKG-INFO
collective.js.formvalidation.egg-info/SOURCES.txt
collective.js.formvalidation.egg-info/dependency_links.txt
collective.js.formvalidation.egg-info/entry_points.txt
collective.js.formvalidation.egg-info/namespace_packages.txt
collective.js.formvalidation.egg-info/not-zip-safe
collective.js.formvalidation.egg-info/requires.txt
collective.js.formvalidation.egg-info/top_level.txt
collective/js/__init__.py
collective/js/formvalidation/__init__.py
collective/js/formvalidation/configure.zcml
collective/js/formvalidation/interfaces.py
collective/js/formvalidation/tests.py
collective/js/formvalidation/version.txt
collective/js/formvalidation/browser/__init__.py
collective/js/formvalidation/browser/configure.zcml
collective/js/formvalidation/browser/javascripts/additional-methods.js
collective/js/formvalidation/browser/javascripts/additional-methods.min.js
collective/js/formvalidation/browser/javascripts/jquery.validate.js
collective/js/formvalidation/browser/javascripts/jquery.validate.min.js
collective/js/formvalidation/browser/javascripts/version.txt
collective/js/formvalidation/profiles/default/browserlayer.xml
collective/js/formvalidation/profiles/default/jsregistry.xml
collective/js/formvalidation/profiles/default/metadata.xml
docs/HISTORY.txt
docs/INSTALL.txt
docs/LICENSE.GPL
docs/LICENSE.txt