Metadata-Version: 1.0
Name: collective.js.formvalidation
Version: 1.0b1
Summary: UNKNOWN
Home-page: https://github.com/collective/collective.js.formvalidation
Author: Timo Stollenwerk
Author-email: contact@timostollenwerk.net
License: GPL
Keywords: plone zope javascript jquery form validation
Platform: UNKNOWN
Classifier: Framework :: Plone
Classifier: Programming Language :: Python
